Metadata-Version: 1.0
Name: distribution-by-benson
Version: 0.1
Summary: Gaussian and Binomial distributions
Home-page: UNKNOWN
Author: Benson Sabu
Author-email: abcd@you.com
License: UNKNOWN
Platform: UNKNOWN
